tspart/__init__.py
tspart/_draw.py
tspart/_files.py
tspart/_helpers.py
tspart/_image.py
tspart/neos.py
tspart/studio.py
tspart/tsp.py
tspart/voronoi.py
tspart-0.7.17.dist-info/LICENSE
tspart-0.7.17.dist-info/WHEEL
tspart-0.7.17.dist-info/METADATA
tspart-0.7.17.dist-info/RECORD
