Metadata-Version: 2.1
Name: tspart
Version: 0.7.17
Summary: TSP Art Module for Python
Author-email: Ella Jameson <ellagjameson@gmail.com>
Requires-Python: >=3.10
Classifier: Development Status :: 4 - Beta
Classifier: License :: OSI Approved :: GNU General Public License v3 or later (GPLv3+)
Classifier: Programming Language :: Python
Classifier: Programming Language :: Python :: 3
Classifier: Programming Language :: Python :: 3.10
Classifier: Programming Language :: Python :: 3.11
Classifier: Programming Language :: Python :: 3.12
Classifier: Programming Language :: Python :: 3 :: Only
Classifier: Topic :: Artistic Software
Classifier: Topic :: Multimedia :: Graphics
Classifier: Topic :: Multimedia :: Graphics :: Graphics Conversion
Requires-Dist: scipy
Requires-Dist: numpy
Requires-Dist: etatime
Requires-Dist: Pillow
Requires-Dist: ortools
Project-URL: documentation, https://tspart.readthedocs.io/en/latest/index.html
Project-URL: homepage, https://github.com/nimaid/python-tspart
Project-URL: issues, https://github.com/nimaid/python-tspart/issues
Project-URL: repository, https://github.com/nimaid/python-tspart
